splunk_logging/__init__.py
splunk_logging/formatters.py
splunk_logging/forwarders.py
splunk_logging/handlers.py
python_splunk_logging-1.0.0.dist-info/METADATA
python_splunk_logging-1.0.0.dist-info/WHEEL
python_splunk_logging-1.0.0.dist-info/licenses/LICENSE
python_splunk_logging-1.0.0.dist-info/RECORD
