Metadata-Version: 2.4
Name: python-splunk-logging
Version: 1.0.0
Summary: Python logging module for logging json formatted log messages to a HTTP Event Collector (HEC).
Project-URL: repository, https://github.com/splunk/python-splunk-logging
Author-email: Alexander Baker <alexb@splunk.com>, Eric Li <ericli@splunk.com>
License-Expression: Apache-2.0
License-File: LICENSE
Keywords: cisco,hec,http,json,logging,splunk
Classifier: Development Status :: 5 - Production/Stable
Classifier: Intended Audience :: Developers
Classifier: License :: OSI Approved :: Apache Software License
Classifier: Natural Language :: English
Classifier: Operating System :: OS Independent
Classifier: Programming Language :: Python :: 3
Classifier: Topic :: Software Development :: Libraries :: Python Modules
Classifier: Typing :: Typed
Requires-Python: >=3.9
Requires-Dist: httpx>=0.28.1
Requires-Dist: python-dateutil>=2.9.0
